django_dbsync/__init__.py
django_dbsync/apps.py
django_dbsync/settings.py
django_dbsync/core/__init__.py
django_dbsync/core/database_inspector.py
django_dbsync/core/exceptions.py
django_dbsync/core/field_mapper.py
django_dbsync/core/sync_engine.py
django_dbsync/core/sync_engine_backup.py
django_dbsync/management/__init__.py
django_dbsync/management/commands/__init__.py
django_dbsync/management/commands/dbcheck.py
django_dbsync/management/commands/dbsync.py
django_dbsync/templates/django_dbsync/orphaned_tables.html
django_dbsync/templates/django_dbsync/sync_report.html
django_dbsync/utils/__init__.py
django_dbsync/utils/helpers.py
django_dbsync/utils/validators.py
django_dbsync-1.2.6.dist-info/METADATA
django_dbsync-1.2.6.dist-info/WHEEL
django_dbsync-1.2.6.dist-info/entry_points.txt
django_dbsync-1.2.6.dist-info/top_level.txt
django_dbsync-1.2.6.dist-info/RECORD
