Metadata-Version: 2.4
Name: django-dbsync
Version: 1.2.6
Summary: Intelligent database synchronization tool for Django projects
Home-page: https://github.com/Lovedazzell/django-dbsync
Author: love dazzell
Author-email: lovepreetdazzell@gmail.com
License: MIT
Project-URL: Bug Tracker, https://github.com/Lovedazzell/django-dbsync/issues
Project-URL: Documentation, https://django-dbsync.readthedocs.io/
Project-URL: Source Code, https://github.com/Lovedazzell/django-dbsync
Keywords: django database sync migration schema synchronization
Platform: any
Classifier: Development Status :: 5 - Production/Stable
Classifier: Environment :: Web Environment
Classifier: Framework :: Django
Classifier: Framework :: Django :: 3.2
Classifier: Framework :: Django :: 4.0
Classifier: Framework :: Django :: 4.1
Classifier: Framework :: Django :: 4.2
Classifier: Framework :: Django :: 5.0
Classifier: Intended Audience :: Developers
Classifier: License :: OSI Approved :: MIT License
Classifier: Operating System :: OS Independent
Classifier: Programming Language :: Python
Classifier: Programming Language :: Python :: 3
Classifier: Programming Language :: Python :: 3.8
Classifier: Programming Language :: Python :: 3.9
Classifier: Programming Language :: Python :: 3.10
Classifier: Programming Language :: Python :: 3.11
Classifier: Programming Language :: Python :: 3.12
Classifier: Topic :: Database
Classifier: Topic :: Internet :: WWW/HTTP :: Dynamic Content
Classifier: Topic :: Software Development :: Libraries :: Application Frameworks
Classifier: Topic :: Software Development :: Libraries :: Python Modules
Requires-Python: >=3.8
Requires-Dist: Django<6.0,>=3.2
Requires-Dist: colorama>=0.4.0
Requires-Dist: tabulate>=0.8.0
Provides-Extra: dev
Requires-Dist: pytest>=6.0; extra == "dev"
Requires-Dist: pytest-django>=4.0; extra == "dev"
Requires-Dist: pytest-cov>=2.0; extra == "dev"
Requires-Dist: black>=22.0; extra == "dev"
Requires-Dist: flake8>=4.0; extra == "dev"
Requires-Dist: isort>=5.0; extra == "dev"
Requires-Dist: mypy>=0.900; extra == "dev"
Provides-Extra: mysql
Requires-Dist: mysqlclient>=2.0; extra == "mysql"
Provides-Extra: postgresql
Requires-Dist: psycopg2-binary>=2.8; extra == "postgresql"
Provides-Extra: oracle
Requires-Dist: cx_Oracle>=8.0; extra == "oracle"
Dynamic: author
Dynamic: author-email
Dynamic: classifier
Dynamic: description
Dynamic: description-content-type
Dynamic: home-page
Dynamic: keywords
Dynamic: license
Dynamic: platform
Dynamic: project-url
Dynamic: provides-extra
Dynamic: requires-dist
Dynamic: requires-python
Dynamic: summary
